HW/HW2/adder.v
`define AND and #50
`define OR or #50
`define NOT not #50
`define XOR xor #50

module behavioralFullAdder(sum, carryout, a, b, carryin);
  output sum, carryout;
  input a, b, carryin;
  assign {carryout, sum} = a + b + carryin;
endmodule

module structuralFullAdder(out, carryout, a, b, carryin);
  output out, carryout;
  input a, b, carryin;
  wire AxorB, AandB, XandC;
  `XOR xorgate0(AxorB, a, b);
  `XOR xorgate1(out, AxorB, carryin);
  `AND andgate0(AandB, a, b);
  `AND andgate1(XandC, AxorB, carryin);
  `OR orgate0(carryout, AandB, XandC);
endmodule

module testFullAdder;
  reg a, b, carryin;
  wire sum, carryout;
  // behavioralFullAdder adder (sum, carryout, a, b, carryin);
  structuralFullAdder adder (sum, carryout, a, b, carryin);

  initial begin
    $dumpfile("adder.vcd");
    $dumpvars(0, testFullAdder);

    $display("A B Ci | Co S | Expected Output");
    a = 0; b = 0; carryin = 0; #1000
    $display("%b %b  %b |  %b %b | Both False", a, b, carryin, carryout, sum);
    a = 0; b = 1; carryin = 0; #1000
    $display("%b %b  %b |  %b %b | Sum True", a, b, carryin, carryout, sum);
    a = 1; b = 0; carryin = 0; #1000
    $display("%b %b  %b |  %b %b | Sum True", a, b, carryin, carryout, sum);
    a = 1; b = 1; carryin = 0; #1000
    $display("%b %b  %b |  %b %b | CarryOut True", a, b, carryin, carryout, sum);
    a = 0; b = 0; carryin = 1; #1000
    $display("%b %b  %b |  %b %b | Sum True", a, b, carryin, carryout, sum);
    a = 0; b = 1; carryin = 1; #1000
    $display("%b %b  %b |  %b %b | CarryOut True", a, b, carryin, carryout, sum);
    a = 1; b = 0; carryin = 1; #1000
    $display("%b %b  %b |  %b %b | CarryOut True", a, b, carryin, carryout, sum);
    a = 1; b = 1; carryin = 1; #1000
    $display("%b %b  %b |  %b %b | Both True", a, b, carryin, carryout, sum);
  end
endmodule

HW/HW2/adder.vcd
$date
	Wed Sep 23 17:10:58 2015
$end
$version
	Icarus Verilog
$end
$timescale
	1s
$end
$scope module testFullAdder $end
$var wire 1 ! carryout $end
$var wire 1 " sum $end
$var reg 1 # a $end
$var reg 1 $ b $end
$var reg 1 % carryin $end
$scope module adder $end
$var wire 1 & AandB $end
$var wire 1 ' AxorB $end
$var wire 1 ( XandC $end
$var wire 1 ) a $end
$var wire 1 * b $end
$var wire 1 + carryin $end
$var wire 1 ! carryout $end
$var wire 1 " out $end
$upscope $end
$upscope $end
$enddefinitions $end
#0
$dumpvars
0+
0*
0)
z(
z'
z&
0%
0$
0#
x"
x!
$end
#50
0(
0&
0'
#100
0!
0"
#1000
1$
1*
#1050
1'
#1100
1"
#2000
0$
0*
1#
1)
#3000
1$
1*
#3050
0'
1&
#3100
0"
1!
#4000
1%
1+
0$
0*
0#
0)
#4050
1"
0&
#4100
0!
#5000
1$
1*
#5050
1'
#5100
0"
1(
#5150
1!
#6000
0$
0*
1#
1)
#7000
1$
1*
#7050
0'
1&
#7100
1"
0(
