HW/HW2/multiplexer.v
`define AND and #50
`define OR or #50
`define NOT not #50
`define XOR xor #50

module behavioralMultiplexer(out, address0, address1, in0, in1, in2, in3);
  output out;
  input address0, address1;
  input in0, in1, in2, in3;
  wire[3:0] inputs = {in3, in2, in1, in0};
  wire[1:0] address = {address1, address0};
  assign out = inputs[address];
endmodule

module structuralMultiplexer(out, address0, address1, in0, in1, in2, in3);
  output out;
  input address0, address1;
  input in0, in1, in2, in3;
  wire nA0, nA1;
  wire nA0andnA1, nA0andA1, A0andnA1, A0andA1;
  wire nA0andnA1andin0, nA0andA1andin1, A0andnA1andin2, A0andA1andin3;
  wire nai0, nai1, nai2, nai3;
  wire ai0andnai1, nai0andai1, ai2andnai3, nai2andai3;
  wire ai0xorai1, ai2xorai3;
  wire ai0xnorai1, ai2xnorai3;
  wire ai0xorai1andai0xnorai1, ai2xorai3andai2xnorai3;
  `NOT notgate0(nA0, address0);
  `NOT notgate1(nA1, address1);
  `AND andgate0(nA0andnA1, nA0, nA1);
  `AND andgate1(nA0andA1, nA0, address1);
  `AND andgate2(A0andnA1, address0, nA1);
  `AND andgate3(A0andA1, address0, address1);
  `AND andgate4(nA0andnA1andin0, nA0andnA1, in0);
  `AND andgate5(A0andnA1andin1, A0andnA1, in1);
  `AND andgate6(nA0andA1andin2, nA0andA1, in2);
  `AND andgate7(A0andA1andin3, A0andA1, in3);
  `XOR xorgate0(ai0xorai1, nA0andnA1andin0, nA0andA1andin2);
  `XOR xorgate1(ai2xorai3, A0andnA1andin1, A0andA1andin3);
  `XOR xorgate2(out, ai0xorai1, ai2xorai3);
  endmodule


module testMultiplexer;
  reg address0, address1;
  reg in0, in1, in2, in3;
  wire out;
  integer i;
  // behavioralMultiplexer multiplexer (out, address0, address1, in0, in1, in2, in3);
  structuralMultiplexer multiplexer (out, address0, address1, in0, in1, in2, in3);

  initial begin
    $dumpfile("multiplexer.vcd");
    $dumpvars(0, testMultiplexer);

  	$display("Concise Table:");
    $display("A1 A0 | I0 I1 I2 I3 | O | Expected Output");
    address1 = 0; address0 = 0;
    $display(" %b  %b |  X  X  X  X | X | Input%d", address1, address0, 2 * address1 + 1 * address0);
    address1 = 0; address0 = 1;
    $display(" %b  %b |  X  X  X  X | X | Input%d", address1, address0, 2 * address1 + 1 * address0);
    address1 = 1; address0 = 0;
    $display(" %b  %b |  X  X  X  X | X | Input%d", address1, address0, 2 * address1 + 1 * address0);
    address1 = 1; address0 = 1;
    $display(" %b  %b |  X  X  X  X | X | Input%d", address1, address0, 2 * address1 + 1 * address0);
  	$display("Full Table:");
    $display("A1 A0 | I0 I1 I2 I3 | O | Expected Output");
    for (i = 0; i < 64; i = i + 1) begin
      address1 = i[5];
      address0 = i[4];
      in0 = i[3];
      in1 = i[2];
      in2 = i[1];
      in3 = i[0];
      #1000
      $display(" %b  %b |  %b  %b  %b  %b | %b | Input%d", address1, address0, in0, in1, in2, in3, out, 2 * address1 + 1 * address0);
    end
  end
endmodule

HW/HW2/multiplexer.vcd
$date
	Wed Sep 23 17:10:59 2015
$end
$version
	Icarus Verilog
$end
$timescale
	1s
$end
$scope module testMultiplexer $end
$var wire 1 ! out $end
$var reg 1 " address0 $end
$var reg 1 # address1 $end
$var integer 32 $ i [31:0] $end
$var reg 1 % in0 $end
$var reg 1 & in1 $end
$var reg 1 ' in2 $end
$var reg 1 ( in3 $end
$scope module multiplexer $end
$var wire 1 ) A0andA1 $end
$var wire 1 * A0andA1andin3 $end
$var wire 1 + A0andnA1 $end
$var wire 1 , A0andnA1andin1 $end
$var wire 1 - address0 $end
$var wire 1 . address1 $end
$var wire 1 / ai0xorai1 $end
$var wire 1 0 ai2xorai3 $end
$var wire 1 1 in0 $end
$var wire 1 2 in1 $end
$var wire 1 3 in2 $end
$var wire 1 4 in3 $end
$var wire 1 5 nA0 $end
$var wire 1 6 nA0andA1 $end
$var wire 1 7 nA0andA1andin2 $end
$var wire 1 8 nA0andnA1 $end
$var wire 1 9 nA0andnA1andin0 $end
$var wire 1 : nA1 $end
$var wire 1 ! out $end
$upscope $end
$upscope $end
$enddefinitions $end
#0
$dumpvars
z:
z9
x8
z7
z6
z5
04
03
02
01
x0
x/
0.
0-
z,
z+
z*
z)
0(
0'
0&
0%
b0 $
0#
0"
x!
$end
#50
0*
07
0,
09
0)
0+
06
15
1:
#100
00
0/
18
#150
0!
#1000
1(
14
b1 $
#2000
0(
04
1'
13
b10 $
#3000
1(
14
b11 $
#4000
0(
04
0'
03
1&
12
b100 $
#5000
1(
14
b101 $
#6000
0(
04
1'
13
b110 $
#7000
1(
14
b111 $
#8000
0(
04
0'
03
0&
02
1%
11
b1000 $
#8050
19
#8100
1/
#8150
1!
#9000
1(
14
b1001 $
#10000
0(
04
1'
13
b1010 $
#11000
1(
14
b1011 $
#12000
0(
04
0'
03
1&
12
b1100 $
#13000
1(
14
b1101 $
#14000
0(
04
1'
13
b1110 $
#15000
1(
14
b1111 $
#16000
0(
04
0'
03
0&
02
0%
01
1"
1-
b10000 $
#16050
09
05
1+
#16100
0/
08
#16150
0!
#17000
1(
14
b10001 $
#18000
0(
04
1'
13
b10010 $
#19000
1(
14
b10011 $
#20000
0(
04
0'
03
1&
12
b10100 $
#20050
1,
#20100
10
#20150
1!
#21000
1(
14
b10101 $
#22000
0(
04
1'
13
b10110 $
#23000
1(
14
b10111 $
#24000
0(
04
0'
03
0&
02
1%
11
b11000 $
#24050
0,
#24100
00
#24150
0!
#25000
1(
14
b11001 $
#26000
0(
04
1'
13
b11010 $
#27000
1(
14
b11011 $
#28000
0(
04
0'
03
1&
12
b11100 $
#28050
1,
#28100
10
#28150
1!
#29000
1(
14
b11101 $
#30000
0(
04
1'
13
b11110 $
#31000
1(
14
b11111 $
#32000
0(
04
0'
03
0&
02
0%
01
0"
0-
1#
1.
b100000 $
#32050
0,
15
0+
0:
#32100
00
16
#32150
0!
#33000
1(
14
b100001 $
#34000
0(
04
1'
13
b100010 $
#34050
17
#34100
1/
#34150
1!
#35000
1(
14
b100011 $
#36000
0(
04
0'
03
1&
12
b100100 $
#36050
07
#36100
0/
#36150
0!
#37000
1(
14
b100101 $
#38000
0(
04
1'
13
b100110 $
#38050
17
#38100
1/
#38150
1!
#39000
1(
14
b100111 $
#40000
0(
04
0'
03
0&
02
1%
11
b101000 $
#40050
07
#40100
0/
#40150
0!
#41000
1(
14
b101001 $
#42000
0(
04
1'
13
b101010 $
#42050
17
#42100
1/
#42150
1!
#43000
1(
14
b101011 $
#44000
0(
04
0'
03
1&
12
b101100 $
#44050
07
#44100
0/
#44150
0!
#45000
1(
14
b101101 $
#46000
0(
04
1'
13
b101110 $
#46050
17
#46100
1/
#46150
1!
#47000
1(
14
b101111 $
#48000
0(
04
0'
03
0&
02
0%
01
1"
1-
b110000 $
#48050
07
05
1)
#48100
0/
06
#48150
0!
#49000
1(
14
b110001 $
#49050
1*
#49100
10
#49150
1!
#50000
0(
04
1'
13
b110010 $
#50050
0*
#50100
00
#50150
0!
#51000
1(
14
b110011 $
#51050
1*
#51100
10
#51150
1!
#52000
0(
04
0'
03
1&
12
b110100 $
#52050
0*
#52100
00
#52150
0!
#53000
1(
14
b110101 $
#53050
1*
#53100
10
#53150
1!
#54000
0(
04
1'
13
b110110 $
#54050
0*
#54100
00
#54150
0!
#55000
1(
14
b110111 $
#55050
1*
#55100
10
#55150
1!
#56000
0(
04
0'
03
0&
02
1%
11
b111000 $
#56050
0*
#56100
00
#56150
0!
#57000
1(
14
b111001 $
#57050
1*
#57100
10
#57150
1!
#58000
0(
04
1'
13
b111010 $
#58050
0*
#58100
00
#58150
0!
#59000
1(
14
b111011 $
#59050
1*
#59100
10
#59150
1!
#60000
0(
04
0'
03
1&
12
b111100 $
#60050
0*
#60100
00
#60150
0!
#61000
1(
14
b111101 $
#61050
1*
#61100
10
#61150
1!
#62000
0(
04
1'
13
b111110 $
#62050
0*
#62100
00
#62150
0!
#63000
1(
14
b111111 $
#63050
1*
#63100
10
#63150
1!
#64000
b1000000 $
